s3zipda.py
s3zipda-0.1.0.dist-info/METADATA
s3zipda-0.1.0.dist-info/WHEEL
s3zipda-0.1.0.dist-info/RECORD
